pvnet_summation/__init__.py
pvnet_summation/load_model.py
pvnet_summation/optimizers.py
pvnet_summation/utils.py
pvnet_summation/data/__init__.py
pvnet_summation/data/datamodule.py
pvnet_summation/models/__init__.py
pvnet_summation/models/base_model.py
pvnet_summation/models/dense_model.py
pvnet_summation/models/horizon_dense_model.py
pvnet_summation/training/__init__.py
pvnet_summation/training/lightning_module.py
pvnet_summation/training/plots.py
pvnet_summation/training/train.py
pvnet_summation-1.1.2.dist-info/licenses/LICENSE
pvnet_summation-1.1.2.dist-info/METADATA
pvnet_summation-1.1.2.dist-info/WHEEL
pvnet_summation-1.1.2.dist-info/top_level.txt
pvnet_summation-1.1.2.dist-info/RECORD
