Metadata-Version: 2.4
Name: PVNet_summation
Version: 1.1.2
Summary: PVNet_summation
Author-email: James Fulton <info@openclimatefix.org>
Requires-Python: <3.14,>=3.11
License-File: LICENSE
Requires-Dist: pvnet>=5.0.0
Requires-Dist: ocf-data-sampler>=0.6.0
Requires-Dist: numpy
Requires-Dist: pandas
Requires-Dist: matplotlib
Requires-Dist: xarray
Requires-Dist: torch>=2.0.0
Requires-Dist: lightning
Requires-Dist: typer
Requires-Dist: wandb
Requires-Dist: huggingface-hub
Requires-Dist: tqdm
Requires-Dist: omegaconf
Requires-Dist: hydra-core
Requires-Dist: rich
Requires-Dist: safetensors
Dynamic: license-file
